tensorflow_metadata/__init__.py
tensorflow_metadata/version.py
tensorflow_metadata/proto/__init__.py
tensorflow_metadata/proto/v0/__init__.py
tensorflow_metadata/proto/v0/anomalies_pb2.py
tensorflow_metadata/proto/v0/derived_feature_pb2.py
tensorflow_metadata/proto/v0/metric_pb2.py
tensorflow_metadata/proto/v0/path_pb2.py
tensorflow_metadata/proto/v0/problem_statement_pb2.py
tensorflow_metadata/proto/v0/schema_pb2.py
tensorflow_metadata/proto/v0/statistics_pb2.py
tensorflow_metadata_czgdp1807-1.18.0.dev1.dist-info/LICENSE
tensorflow_metadata_czgdp1807-1.18.0.dev1.dist-info/METADATA
tensorflow_metadata_czgdp1807-1.18.0.dev1.dist-info/WHEEL
tensorflow_metadata_czgdp1807-1.18.0.dev1.dist-info/namespace_packages.txt
tensorflow_metadata_czgdp1807-1.18.0.dev1.dist-info/top_level.txt
tensorflow_metadata_czgdp1807-1.18.0.dev1.dist-info/RECORD
