Metadata-Version: 2.1
Name: tensorflow-metadata-czgdp1807
Version: 1.18.0.dev1
Summary: Library and standards for schema and statistics.
Download-URL: https://github.com/tensorflow/metadata/tags
Author: Google Inc.
Author-email: tensorflow-extended-dev@googlegroups.com
License: Apache 2.0
Keywords: tensorflow metadata tfx
Classifier: Development Status :: 5 - Production/Stable
Classifier: Intended Audience :: Developers
Classifier: Intended Audience :: Education
Classifier: Intended Audience :: Science/Research
Classifier: License :: OSI Approved :: Apache Software License
Classifier: Operating System :: OS Independent
Classifier: Programming Language :: Python
Classifier: Programming Language :: Python :: 3
Classifier: Programming Language :: Python :: 3.9
Classifier: Programming Language :: Python :: 3.10
Classifier: Programming Language :: Python :: 3.11
Classifier: Programming Language :: Python :: 3.12
Classifier: Programming Language :: Python :: 3.13
Classifier: Programming Language :: Python :: 3 :: Only
Classifier: Topic :: Scientific/Engineering :: Artificial Intelligence
Classifier: Topic :: Scientific/Engineering :: Mathematics
Classifier: Topic :: Software Development
Classifier: Topic :: Software Development :: Libraries
Classifier: Topic :: Software Development :: Libraries :: Python Modules
Requires-Python: >=3.9,<4
License-File: LICENSE
Requires-Dist: absl-py<3.0.0,>=0.9
Requires-Dist: protobuf<4.22,>=4.21.6; python_version < "3.11"
Requires-Dist: googleapis-common-protos<2,>=1.56.4; python_version >= "3.11"
Requires-Dist: protobuf>=4.25.2; python_version >= "3.11"
Provides-Extra: dev
Requires-Dist: precommit; extra == "dev"
Provides-Extra: test
Requires-Dist: pytest<9,>=8; extra == "test"
